setup.py
pinata/__init__.py
pinata/client.py
pinterest_pinata.egg-info/PKG-INFO
pinterest_pinata.egg-info/SOURCES.txt
pinterest_pinata.egg-info/dependency_links.txt
pinterest_pinata.egg-info/requires.txt
pinterest_pinata.egg-info/top_level.txt
pinterest_pinata.egg-info/zip-safe