Metadata-Version: 1.0
Name: pinterest-pinata
Version: 1.1.3
Summary: Pinterest client
Home-page: http://github.com/odynvolk/pinterest-pinata
Author: Alexi Rahman
Author-email: alexi.rahman@r76.se
License: UNKNOWN
Keywords: pinterest api
Platform: UNKNOWN
